[
    {
        "course_reference": {
            "course_number": 432,
            "subjects": [
                "SCANDST",
                "HISTORY"
            ]
        },
        "course_title": "HISTORY OF SCANDINAVIA SINCE 1815",
        "description": "Political, social, economic, and cultural development: political realignments and rise of nationalism, industrialization and rise of liberalism and socialism, democratization, independence struggles and social conflict, evolution of welfare states, World War II and its aftermath.",
        "optimized": null,
        "prerequisites": {
            "course_references": [],
            "prerequisites_text": "Sophomore standing"
        }
    },
    {
        "course_reference": {
            "course_number": 271,
            "subjects": [
                "SCANDST"
            ]
        },
        "course_title": "READINGS IN DANISH LITERATURE",
        "description": "Prose, poetry, and drama read in Danish. Taught extensively in Danish.",
        "optimized": null,
        "prerequisites": {
            "course_references": [
                {
                    "course_number": 222,
                    "subjects": [
                        "SCANDST"
                    ]
                }
            ],
            "prerequisites_text": "SCAND\u00a0ST\u00a0222"
        }
    },
    {
        "course_reference": {
            "course_number": 122,
            "subjects": [
                "SCANDST"
            ]
        },
        "course_title": "SECOND SEMESTER DANISH",
        "description": "For beginning learners of Danish; emphasis on proficiency through speaking, listening, reading, and writing, and on communication in cultural context.",
        "optimized": null,
        "prerequisites": {
            "course_references": [
                {
                    "course_number": 121,
                    "subjects": [
                        "SCANDST"
                    ]
                }
            ],
            "prerequisites_text": "SCAND\u00a0ST\u00a0121"
        }
    },
    {
        "course_reference": {
            "course_number": 999,
            "subjects": [
                "SCANDST"
            ]
        },
        "course_title": "INDEPENDENT READING",
        "description": "Advanced level mentored reading and research for students with dissertator status.",
        "optimized": null,
        "prerequisites": {
            "course_references": [],
            "prerequisites_text": "Consent of instructor"
        }
    },
    {
        "course_reference": {
            "course_number": 132,
            "subjects": [
                "SCANDST"
            ]
        },
        "course_title": "SECOND SEMESTER FINNISH",
        "description": "For beginning learners of Finnish; emphasis on proficiency through speaking, listening, reading, and writing, and on communication in cultural context.",
        "optimized": null,
        "prerequisites": {
            "course_references": [
                {
                    "course_number": 131,
                    "subjects": [
                        "SCANDST"
                    ]
                }
            ],
            "prerequisites_text": "SCAND\u00a0ST\u00a0131"
        }
    },
    {
        "course_reference": {
            "course_number": 421,
            "subjects": [
                "SCANDST"
            ]
        },
        "course_title": "ADVANCED TOPICS IN NORDIC STUDIES",
        "description": "Study of topics in Nordic and Nordic-American history, culture, and/or folklore.",
        "optimized": null,
        "prerequisites": {
            "course_references": [],
            "prerequisites_text": "Junior standing"
        }
    },
    {
        "course_reference": {
            "course_number": 345,
            "subjects": [
                "FOLKLORE",
                "SCANDST",
                "MEDIEVAL",
                "LITTRANS"
            ]
        },
        "course_title": "THE NORDIC STORYTELLER",
        "description": "Exploring the oral nature and performance traditions of folklore, ethnography, tales and ballads, literature and culture from Nordic areas and Scandinavia.",
        "optimized": null,
        "prerequisites": {
            "course_references": [],
            "prerequisites_text": "Satisfied Communications A requirement"
        }
    },
    {
        "course_reference": {
            "course_number": 710,
            "subjects": [
                "SCANDST"
            ]
        },
        "course_title": "TOPICS IN DEPTH",
        "description": "Penetrating study of an important Scandinavian literary or linguistic topic.",
        "optimized": null,
        "prerequisites": {
            "course_references": [],
            "prerequisites_text": "Graduate/professional standing"
        }
    },
    {
        "course_reference": {
            "course_number": 250,
            "subjects": [
                "SCANDST"
            ]
        },
        "course_title": "INTRODUCTION TO SCANDINAVIA",
        "description": "Provides an introductory survey of Scandinavia and Northern Europe. Approaches the source material by focusing on concepts such as environment and sustainability, nation, migration, diversity, family, childhood, happiness, and melancholy. Learn about modern and contemporary Northern European cultures through literature, film, television, music, and other media from Norway, Denmark, Sweden, Iceland, Finland, S\u00e1pmi, or the Baltic countries.",
        "optimized": null,
        "prerequisites": {
            "course_references": [],
            "prerequisites_text": "None"
        }
    },
    {
        "course_reference": {
            "course_number": 415,
            "subjects": [
                "SCANDST"
            ]
        },
        "course_title": "HISTORY OF THE SCANDINAVIAN LANGUAGES II: STANDARD LANGUAGES",
        "description": "Study of Scandinavian languages from the early Scandinavian period to the present day.",
        "optimized": null,
        "prerequisites": {
            "course_references": [],
            "prerequisites_text": "Graduate/professional standing"
        }
    },
    {
        "course_reference": {
            "course_number": 222,
            "subjects": [
                "SCANDST"
            ]
        },
        "course_title": "SECOND YEAR DANISH",
        "description": "Reading of selections from Danish writers, grammar review and conversation.",
        "optimized": null,
        "prerequisites": {
            "course_references": [
                {
                    "course_number": 221,
                    "subjects": [
                        "SCANDST"
                    ]
                }
            ],
            "prerequisites_text": "SCAND\u00a0ST\u00a0221"
        }
    },
    {
        "course_reference": {
            "course_number": 424,
            "subjects": [
                "SCANDST"
            ]
        },
        "course_title": "NINETEENTH-CENTURY SCANDINAVIAN FICTION",
        "description": "Readings in such authors as Hans Christian Andersen, Steen Steensen Blicher, C.J.L. Almquist, Alexis Kivi, Bjornstjerne Bjornson, Jonas Lie, Alexander Kielland, Jens Peter Jacobsen, Henrik Pontoppidan, August Strindberg, Selma Lagerlof, and Johs V. Jensen.",
        "optimized": {
            "course_number": 202,
            "subjects": [
                "SCANDST"
            ]
        },
        "prerequisites": {
            "course_references": [
                {
                    "course_number": 202,
                    "subjects": [
                        "SCANDST"
                    ]
                },
                {
                    "course_number": 212,
                    "subjects": [
                        "SCANDST"
                    ]
                },
                {
                    "course_number": 222,
                    "subjects": [
                        "SCANDST"
                    ]
                }
            ],
            "prerequisites_text": "SCAND\u00a0ST\u00a0202,212,222or graduate/professional standing"
        }
    },
    {
        "course_reference": {
            "course_number": 446,
            "subjects": [
                "FOLKLORE",
                "SCANDST",
                "MEDIEVAL"
            ]
        },
        "course_title": "CELTIC-SCANDINAVIAN CULTURAL INTERRELATIONS",
        "description": "Examination of shared traditions and historical connections between the North and Northwest of Europe. Readings of medieval and pre-modern Scandinavian, Scottish, Welsh and Irish sagas, histories, talkes. Discussion of the role of folklore in modern Celtic and Scandinavian societies.",
        "optimized": null,
        "prerequisites": {
            "course_references": [],
            "prerequisites_text": "Sophomore standing"
        }
    },
    {
        "course_reference": {
            "course_number": 901,
            "subjects": [
                "SCANDST"
            ]
        },
        "course_title": "SEMINAR IN SPECIAL TOPICS",
        "description": "In-depth study of topic of faculty's choice.",
        "optimized": null,
        "prerequisites": {
            "course_references": [],
            "prerequisites_text": "Graduate/professional standing"
        }
    },
    {
        "course_reference": {
            "course_number": 430,
            "subjects": [
                "SCANDST",
                "MEDIEVAL"
            ]
        },
        "course_title": "THE VIKINGS",
        "description": "Within a historical framework, a thorough introduction to the culture, literature, and religion of the Vikings.",
        "optimized": null,
        "prerequisites": {
            "course_references": [],
            "prerequisites_text": "Junior standing"
        }
    },
    {
        "course_reference": {
            "course_number": 320,
            "subjects": [
                "SCANDST",
                "LITTRANS"
            ]
        },
        "course_title": "THE NORDIC CHILD",
        "description": "Astrid Lindgren's Pippi Longstocking is an icon of childhood in the Nordic countries and beyond. Pippi has come to symbolize the Nordic \"autonomous\" child par excellence. Takes up a diverse selection of books and films that represent both the common ideas of the Nordic Child, as well as various elaborations of and exceptions to the idealized norm. Examines a number of the prevalent forms and themes in Nordic children's culture, such as nature, play, school, sexuality, death, loss, and storytelling.",
        "optimized": null,
        "prerequisites": {
            "course_references": [],
            "prerequisites_text": "Satisfied Communications A requirement or graduate/professional standing"
        }
    },
    {
        "course_reference": {
            "course_number": 428,
            "subjects": [
                "SCANDST",
                "LITTRANS"
            ]
        },
        "course_title": "MEMORY AND LITERATURE FROM PROUST TO KNAUSGARD",
        "description": "Investigates the relations between theories of memory, both individual and collective, and modern literary representations of remembering. Survey seminal conceptions of memory in the interdisciplinary field of memory studies, investigating topics such as nostalgia, trauma, personal and cultural identity, war and Holocaust, sites of memory, and autobiographical narrative. Through the avenues opened up by these theoretical frameworks, consider the narrative forms as well as the ethical and political dimensions of remembering in major novels by Marcel Proust, W. G. Sebald, and Karl Ove Knausgard.",
        "optimized": null,
        "prerequisites": {
            "course_references": [],
            "prerequisites_text": "Sophomore standing"
        }
    },
    {
        "course_reference": {
            "course_number": 131,
            "subjects": [
                "SCANDST"
            ]
        },
        "course_title": "FIRST SEMESTER FINNISH",
        "description": "For beginning learners of Finnish; emphasis on proficiency through speaking, listening, reading, and writing, and on communication in cultural context.",
        "optimized": null,
        "prerequisites": {
            "course_references": [],
            "prerequisites_text": "None"
        }
    },
    {
        "course_reference": {
            "course_number": 577,
            "subjects": [
                "SCANDST",
                "HISTORY"
            ]
        },
        "course_title": "CONTEMPORARY SCANDINAVIA: POLITICS AND HISTORY",
        "description": "Social, economic, and ideological changes, institutions, and movements and their relationships with the political processes and structures in the Nordic states.",
        "optimized": null,
        "prerequisites": {
            "course_references": [],
            "prerequisites_text": "Junior standing"
        }
    },
    {
        "course_reference": {
            "course_number": 419,
            "subjects": [
                "SCANDST"
            ]
        },
        "course_title": "SCANDINAVIAN CHILDREN'S LITERATURE",
        "description": "Forms and themes of Scandinavian children's literature from the nineteenth century to the present. Exploration of the dominant concerns of authors, adult and non-adult audiences. Film adaptations and Scandinavian-American materials included.",
        "optimized": {
            "course_number": 202,
            "subjects": [
                "SCANDST"
            ]
        },
        "prerequisites": {
            "course_references": [
                {
                    "course_number": 202,
                    "subjects": [
                        "SCANDST"
                    ]
                },
                {
                    "course_number": 212,
                    "subjects": [
                        "SCANDST"
                    ]
                },
                {
                    "course_number": 222,
                    "subjects": [
                        "SCANDST"
                    ]
                }
            ],
            "prerequisites_text": "Junior standing andSCAND\u00a0ST\u00a0202,212, or222, or graduate/professional standing"
        }
    },
    {
        "course_reference": {
            "course_number": 121,
            "subjects": [
                "SCANDST"
            ]
        },
        "course_title": "FIRST SEMESTER DANISH",
        "description": "For beginning learners of Danish; emphasis on proficiency through speaking, listening, reading, and writing, and on communication in cultural context.",
        "optimized": null,
        "prerequisites": {
            "course_references": [],
            "prerequisites_text": "None"
        }
    },
    {
        "course_reference": {
            "course_number": 681,
            "subjects": [
                "SCANDST"
            ]
        },
        "course_title": "SENIOR HONORS THESIS",
        "description": "Mentored individual research and study for students completing a thesis in an Honors program.",
        "optimized": null,
        "prerequisites": {
            "course_references": [],
            "prerequisites_text": "Consent of instructor"
        }
    },
    {
        "course_reference": {
            "course_number": 102,
            "subjects": [
                "SCANDST"
            ]
        },
        "course_title": "SECOND SEMESTER NORWEGIAN",
        "description": "For beginning learners of Norwegian; emphasis on proficiency through speaking, listening, reading, and writing, and on communication in cultural context.",
        "optimized": null,
        "prerequisites": {
            "course_references": [
                {
                    "course_number": 101,
                    "subjects": [
                        "SCANDST"
                    ]
                }
            ],
            "prerequisites_text": "SCAND\u00a0ST\u00a0101"
        }
    },
    {
        "course_reference": {
            "course_number": 423,
            "subjects": [
                "SCANDST"
            ]
        },
        "course_title": "THE DRAMA OF AUGUST STRINDBERG",
        "description": "Ideas and dramatic practice in the plays of August Strindberg.",
        "optimized": {
            "course_number": 212,
            "subjects": [
                "SCANDST"
            ]
        },
        "prerequisites": {
            "course_references": [
                {
                    "course_number": 202,
                    "subjects": [
                        "SCANDST"
                    ]
                },
                {
                    "course_number": 212,
                    "subjects": [
                        "SCANDST"
                    ]
                },
                {
                    "course_number": 222,
                    "subjects": [
                        "SCANDST"
                    ]
                }
            ],
            "prerequisites_text": "SCAND\u00a0ST\u00a0202,212,222or graduate/professional standing"
        }
    },
    {
        "course_reference": {
            "course_number": 634,
            "subjects": [
                "SCANDST"
            ]
        },
        "course_title": "SURVEY OF SCANDINAVIAN LITERATURE: 1500-1800",
        "description": "Survey representative literary texts from Scandinavia spanning through Reformation, Renaissance, Baroque, Rococo and Pre-Romanticism, including historical context.",
        "optimized": null,
        "prerequisites": {
            "course_references": [],
            "prerequisites_text": "Junior standing"
        }
    },
    {
        "course_reference": {
            "course_number": 520,
            "subjects": [
                "SCANDST"
            ]
        },
        "course_title": "SPECIAL TOPICS",
        "description": "Special topics in Scandinavian culture, literature, and linguistics.",
        "optimized": null,
        "prerequisites": {
            "course_references": [],
            "prerequisites_text": "Junior standing"
        }
    },
    {
        "course_reference": {
            "course_number": 342,
            "subjects": [
                "FOLKLORE",
                "RELIGST",
                "SCANDST",
                "MEDIEVAL"
            ]
        },
        "course_title": "NORDIC MYTHOLOGY",
        "description": "Mythology, literature, ritual, traditions, medieval folklore, and religion from Nordic areas and Scandinavia.",
        "optimized": null,
        "prerequisites": {
            "course_references": [],
            "prerequisites_text": "Sophomore standing"
        }
    },
    {
        "course_reference": {
            "course_number": 348,
            "subjects": [
                "SCANDST"
            ]
        },
        "course_title": "THE SECOND WORLD WAR IN NORDIC CULTURE",
        "description": "How have the wartime issues of occupation, resistance, collaboration, neutrality, and the Holocaust been addressed in Nordic culture? During the Second World War, Norway and Denmark were invaded and occupied by Nazi Germany, while Sweden remained neutral and Finland fought against the Soviet Union. Resistance movements developed in the occupied countries, but some Norwegians and Danes collaborated with the occupying power and were tried for treason after the war. Become familiar with the basic history of the period by reading texts of various sorts (essays, novels, diaries, poetry, memoir) that were written during the war years and since. Through analyzing films and works of fiction, in addition to historical writing, learn how the Second World War and the Holocaust have been represented and remembered in the Nordic countries.",
        "optimized": null,
        "prerequisites": {
            "course_references": [],
            "prerequisites_text": "Sophomore standing"
        }
    },
    {
        "course_reference": {
            "course_number": 426,
            "subjects": [
                "SCANDST"
            ]
        },
        "course_title": "KIERKEGAARD AND SCANDINAVIAN LITERATURE",
        "description": "An introduction to Danish philosopher S\u00f8ren Kierkegaard and existentialism in Scandinavian literature. An overview into Kierkegaard's work in translation and his influence on a number of Scandinavian writers from the 19th century to the 21st.",
        "optimized": null,
        "prerequisites": {
            "course_references": [],
            "prerequisites_text": "Sophomore standing"
        }
    },
    {
        "course_reference": {
            "course_number": 440,
            "subjects": [
                "FOLKLORE",
                "SCANDST"
            ]
        },
        "course_title": "SCANDINAVIAN AMERICAN FOLKLORE",
        "description": "Examines the verbal, musical, customary, and material folklore of Scandinavian Americans, with emphasis on the upper Midwest.",
        "optimized": null,
        "prerequisites": {
            "course_references": [],
            "prerequisites_text": "Junior standing"
        }
    },
    {
        "course_reference": {
            "course_number": 296,
            "subjects": [
                "SCANDST"
            ]
        },
        "course_title": "THE SCANDINAVIAN HERITAGE IN AMERICA",
        "description": "Nineteenth century Scandinavian immigration.",
        "optimized": null,
        "prerequisites": {
            "course_references": [],
            "prerequisites_text": "Satisfied Communications A requirement"
        }
    },
    {
        "course_reference": {
            "course_number": 410,
            "subjects": [
                "SCANDST"
            ]
        },
        "course_title": "INTRODUCTION TO SCANDINAVIAN LINGUISTICS",
        "description": "Scandinavia as a linguistic area. The main historical developments and structural features of the Scandinavian languages.",
        "optimized": null,
        "prerequisites": {
            "course_references": [],
            "prerequisites_text": "Graduate/professional standing"
        }
    },
    {
        "course_reference": {
            "course_number": 635,
            "subjects": [
                "SCANDST"
            ]
        },
        "course_title": "SURVEY OF SCANDINAVIAN LITERATURE: 1800-1890",
        "description": "Survey representative literary texts from Scandinavia spanning eras including Romanticism, Realism, and Naturalism; includes historical context.",
        "optimized": {
            "course_number": 202,
            "subjects": [
                "SCANDST"
            ]
        },
        "prerequisites": {
            "course_references": [
                {
                    "course_number": 202,
                    "subjects": [
                        "SCANDST"
                    ]
                },
                {
                    "course_number": 212,
                    "subjects": [
                        "SCANDST"
                    ]
                },
                {
                    "course_number": 222,
                    "subjects": [
                        "SCANDST"
                    ]
                }
            ],
            "prerequisites_text": "SCAND\u00a0ST\u00a0202,212,222or graduate/professional standing"
        }
    },
    {
        "course_reference": {
            "course_number": 211,
            "subjects": [
                "SCANDST"
            ]
        },
        "course_title": "SECOND YEAR SWEDISH",
        "description": "Reading of selections from Swedish writers, grammar review and conversation.",
        "optimized": null,
        "prerequisites": {
            "course_references": [
                {
                    "course_number": 112,
                    "subjects": [
                        "SCANDST"
                    ]
                }
            ],
            "prerequisites_text": "SCAND\u00a0ST\u00a0112"
        }
    },
    {
        "course_reference": {
            "course_number": 299,
            "subjects": [
                "SCANDST"
            ]
        },
        "course_title": "DIRECTED STUDY",
        "description": "Directed study projects as arranged with a faculty member.",
        "optimized": null,
        "prerequisites": {
            "course_references": [],
            "prerequisites_text": "Consent of instructor"
        }
    },
    {
        "course_reference": {
            "course_number": 434,
            "subjects": [
                "SCANDST"
            ]
        },
        "course_title": "THE ART OF ISAK DINESEN/KAREN BLIXEN",
        "description": "Blixen's tales and biographical fiction; themes of gender, power, dreams, and love.",
        "optimized": {
            "course_number": 202,
            "subjects": [
                "SCANDST"
            ]
        },
        "prerequisites": {
            "course_references": [
                {
                    "course_number": 202,
                    "subjects": [
                        "SCANDST"
                    ]
                },
                {
                    "course_number": 212,
                    "subjects": [
                        "SCANDST"
                    ]
                },
                {
                    "course_number": 222,
                    "subjects": [
                        "SCANDST"
                    ]
                }
            ],
            "prerequisites_text": "SCAND\u00a0ST\u00a0202,212,222or graduate/professional standing"
        }
    },
    {
        "course_reference": {
            "course_number": 475,
            "subjects": [
                "SCANDST"
            ]
        },
        "course_title": "THE WRITINGS OF HANS CHRISTIAN ANDERSEN FOR SCANDINAVIAN MAJORS",
        "description": "In-depth discussion of selected texts, historical and literary background material, application and discussion of pertinent literary criticism.",
        "optimized": {
            "course_number": 202,
            "subjects": [
                "SCANDST"
            ]
        },
        "prerequisites": {
            "course_references": [
                {
                    "course_number": 202,
                    "subjects": [
                        "SCANDST"
                    ]
                },
                {
                    "course_number": 212,
                    "subjects": [
                        "SCANDST"
                    ]
                },
                {
                    "course_number": 222,
                    "subjects": [
                        "SCANDST"
                    ]
                }
            ],
            "prerequisites_text": "SCAND\u00a0ST\u00a0202,212,222or graduate/professional standing"
        }
    },
    {
        "course_reference": {
            "course_number": 431,
            "subjects": [
                "SCANDST",
                "HISTORY"
            ]
        },
        "course_title": "HISTORY OF SCANDINAVIA TO 1815",
        "description": "Political, social, economic, and cultural developments of Scandinavia through the \"Viking Age\" to the break-up of Sweden-Finland and Denmark-Norway; emphasis on the interplay between social and political forces and institutions and the area's relationship with the rest of Europe.",
        "optimized": null,
        "prerequisites": {
            "course_references": [],
            "prerequisites_text": "Sophomore standing"
        }
    },
    {
        "course_reference": {
            "course_number": 276,
            "subjects": [
                "SCANDST"
            ]
        },
        "course_title": "CULTURE & COMMUNITY IN SCANDINAVIA",
        "description": "An extensive, wide-ranging introduction to the cultures of and community in the Scandinavian and Nordic Countries. Through a diverse series of guest lectures and discussions, explore the culture, arts, geography, history, religion, languages, music, literature, politics etc. of the Scandinavian countries.",
        "optimized": null,
        "prerequisites": {
            "course_references": [],
            "prerequisites_text": "None"
        }
    },
    {
        "course_reference": {
            "course_number": 409,
            "subjects": [
                "SCANDST",
                "MEDIEVAL"
            ]
        },
        "course_title": "SURVEY OF OLD NORSE-ICELANDIC LITERATURE",
        "description": "Eddic and skaldic poetry; homilies and saints' lives, kings' sagas, sagas of the Icelanders; mythical-heroic sagas and romances; rimur.",
        "optimized": null,
        "prerequisites": {
            "course_references": [
                {
                    "course_number": 407,
                    "subjects": [
                        "SCANDST",
                        "MEDIEVAL"
                    ]
                }
            ],
            "prerequisites_text": "MEDIEVAL/\u200bSCAND\u00a0ST\u00a0\u00a0407or graduate/professional standing"
        }
    },
    {
        "course_reference": {
            "course_number": 450,
            "subjects": [
                "SCANDST"
            ]
        },
        "course_title": "SCANDINAVIAN DECADENCE IN ITS EUROPEAN CONTEXT",
        "description": "Examines the European context of literary decadence (Baudelaire, Huysmans, Wilde) and how it inspired some of Scandinavia's most important writers (Strindberg, Hamsun, Jacobsen).",
        "optimized": {
            "course_number": 202,
            "subjects": [
                "SCANDST"
            ]
        },
        "prerequisites": {
            "course_references": [
                {
                    "course_number": 202,
                    "subjects": [
                        "SCANDST"
                    ]
                },
                {
                    "course_number": 212,
                    "subjects": [
                        "SCANDST"
                    ]
                },
                {
                    "course_number": 222,
                    "subjects": [
                        "SCANDST"
                    ]
                }
            ],
            "prerequisites_text": "SCAND\u00a0ST\u00a0202,212,222or graduate/professional standing"
        }
    },
    {
        "course_reference": {
            "course_number": 111,
            "subjects": [
                "SCANDST"
            ]
        },
        "course_title": "FIRST SEMESTER SWEDISH",
        "description": "For beginning learners of Swedish; emphasis on proficiency through speaking, listening, reading, and writing, and on communication in cultural context.",
        "optimized": null,
        "prerequisites": {
            "course_references": [],
            "prerequisites_text": "None"
        }
    },
    {
        "course_reference": {
            "course_number": 427,
            "subjects": [
                "SCANDST"
            ]
        },
        "course_title": "CONTEMPORARY SCANDINAVIAN LITERATURE",
        "description": "Twentieth-century literary traditions and experiments, with attention to major movements, genres, and authors.",
        "optimized": {
            "course_number": 202,
            "subjects": [
                "SCANDST"
            ]
        },
        "prerequisites": {
            "course_references": [
                {
                    "course_number": 202,
                    "subjects": [
                        "SCANDST"
                    ]
                },
                {
                    "course_number": 212,
                    "subjects": [
                        "SCANDST"
                    ]
                },
                {
                    "course_number": 222,
                    "subjects": [
                        "SCANDST"
                    ]
                }
            ],
            "prerequisites_text": "SCAND\u00a0ST\u00a0202,212,222or graduate/professional standing"
        }
    },
    {
        "course_reference": {
            "course_number": 101,
            "subjects": [
                "SCANDST"
            ]
        },
        "course_title": "FIRST SEMESTER NORWEGIAN",
        "description": "For beginning learners of Norwegian; emphasis on proficiency through speaking, listening, reading, and writing, and on communication in cultural context.",
        "optimized": null,
        "prerequisites": {
            "course_references": [],
            "prerequisites_text": "None"
        }
    },
    {
        "course_reference": {
            "course_number": 443,
            "subjects": [
                "FOLKLORE",
                "SCANDST"
            ]
        },
        "course_title": "SAMI CULTURE, YESTERDAY AND TODAY",
        "description": "Interdisciplinary study of Sami (Lapp) people of Scandinavia past and present. Indigenous modes of expression and worldview, contemporary cultural and political activism. Extensive discussion of connections to Native American and Inuit experiences; rise of U.S. and other indigenous peoples' movements.",
        "optimized": null,
        "prerequisites": {
            "course_references": [],
            "prerequisites_text": "Junior standing"
        }
    },
    {
        "course_reference": {
            "course_number": 407,
            "subjects": [
                "SCANDST",
                "MEDIEVAL"
            ]
        },
        "course_title": "INTRODUCTORY OLD NORSE",
        "description": "Designed with a linguistic purpose: to obtain a reading knowledge of Old Norse-Icelandic through the study of Old Icelandic grammar and selections of Old Norse-Icelandic texts.",
        "optimized": null,
        "prerequisites": {
            "course_references": [],
            "prerequisites_text": "Sophomore standing"
        }
    },
    {
        "course_reference": {
            "course_number": 235,
            "subjects": [
                "FOLKLORE",
                "SCANDST",
                "MEDIEVAL"
            ]
        },
        "course_title": "THE WORLD OF SAGAS",
        "description": "The Icelandic sagas viewed in their social, cultural, and literary contexts. An introduction to one of the greatest bodies of vernacular literature of the early Middle Ages.",
        "optimized": null,
        "prerequisites": {
            "course_references": [],
            "prerequisites_text": "None"
        }
    },
    {
        "course_reference": {
            "course_number": 212,
            "subjects": [
                "SCANDST"
            ]
        },
        "course_title": "SECOND YEAR SWEDISH",
        "description": "Reading of selections from Swedish writers, grammar review and conversation.",
        "optimized": null,
        "prerequisites": {
            "course_references": [
                {
                    "course_number": 211,
                    "subjects": [
                        "SCANDST"
                    ]
                }
            ],
            "prerequisites_text": "SCAND\u00a0ST\u00a0211"
        }
    },
    {
        "course_reference": {
            "course_number": 630,
            "subjects": [
                "SCANDST"
            ]
        },
        "course_title": "FUNDAMENTALS OF BIBLIOGRAPHY AND RESEARCH",
        "description": "Research resources and methodology; scholarly research and literary criticism.",
        "optimized": null,
        "prerequisites": {
            "course_references": [],
            "prerequisites_text": "Junior standing"
        }
    },
    {
        "course_reference": {
            "course_number": 496,
            "subjects": [
                "SCANDST"
            ]
        },
        "course_title": "THE SCANDINAVIAN HERITAGE IN AMERICA",
        "description": "Nineteenth century Scandinavian immigration.",
        "optimized": {
            "course_number": 202,
            "subjects": [
                "SCANDST"
            ]
        },
        "prerequisites": {
            "course_references": [
                {
                    "course_number": 202,
                    "subjects": [
                        "SCANDST"
                    ]
                },
                {
                    "course_number": 212,
                    "subjects": [
                        "SCANDST"
                    ]
                },
                {
                    "course_number": 222,
                    "subjects": [
                        "SCANDST"
                    ]
                }
            ],
            "prerequisites_text": "SCAND\u00a0ST\u00a0202,212,222or graduate/professional standing"
        }
    },
    {
        "course_reference": {
            "course_number": 511,
            "subjects": [
                "SCANDST"
            ]
        },
        "course_title": "PALEOGRAPHY AND PHILOLOGY - OLD NORSE",
        "description": "A history of writing in Iceland 1150-1550 on the basis of manuscripts as principal sources of evidence for Old Norse-Icelandic.",
        "optimized": null,
        "prerequisites": {
            "course_references": [
                {
                    "course_number": 407,
                    "subjects": [
                        "SCANDST",
                        "MEDIEVAL"
                    ]
                }
            ],
            "prerequisites_text": "MEDIEVAL/\u200bSCAND\u00a0ST\u00a0\u00a0407or graduate/professional standing"
        }
    },
    {
        "course_reference": {
            "course_number": 261,
            "subjects": [
                "SCANDST"
            ]
        },
        "course_title": "READINGS IN SWEDISH LITERATURE",
        "description": "Prose, poetry, and drama read in Swedish. Taught extensively in Swedish.",
        "optimized": null,
        "prerequisites": {
            "course_references": [
                {
                    "course_number": 212,
                    "subjects": [
                        "SCANDST"
                    ]
                }
            ],
            "prerequisites_text": "SCAND\u00a0ST\u00a0212"
        }
    },
    {
        "course_reference": {
            "course_number": 439,
            "subjects": [
                "SCANDST"
            ]
        },
        "course_title": "NORDIC FILMMAKERS",
        "description": "Analyze English translations of key works by Nordic filmmakers as well as theories, histories, and the changing meaning of film authorship in the Nordic region.",
        "optimized": null,
        "prerequisites": {
            "course_references": [],
            "prerequisites_text": "Sophomore standing"
        }
    },
    {
        "course_reference": {
            "course_number": 374,
            "subjects": [
                "SCANDST"
            ]
        },
        "course_title": "MASTERPIECES OF SCANDINAVIAN LITERATURE: THE TWENTIETH CENTURY",
        "description": "Through a selection of short texts, novels, and plays, we'll be learning from some of the best: Nobel Laureates (Knut Hamsun, P\u00e4r Lagerkvist), medical doctors (P.C. Jersild), and other provocateurs (August Strindberg, Isak Dinesen, Ingmar Berman, Peter Hoeg, and the rest).",
        "optimized": {
            "course_number": 202,
            "subjects": [
                "SCANDST"
            ]
        },
        "prerequisites": {
            "course_references": [
                {
                    "course_number": 202,
                    "subjects": [
                        "SCANDST"
                    ]
                },
                {
                    "course_number": 212,
                    "subjects": [
                        "SCANDST"
                    ]
                },
                {
                    "course_number": 222,
                    "subjects": [
                        "SCANDST"
                    ]
                }
            ],
            "prerequisites_text": "SCAND\u00a0ST\u00a0202,212, or222"
        }
    },
    {
        "course_reference": {
            "course_number": 221,
            "subjects": [
                "SCANDST"
            ]
        },
        "course_title": "SECOND YEAR DANISH",
        "description": "Reading of selections from Danish writers, grammar review and conversation.",
        "optimized": null,
        "prerequisites": {
            "course_references": [
                {
                    "course_number": 122,
                    "subjects": [
                        "SCANDST"
                    ]
                }
            ],
            "prerequisites_text": "SCAND\u00a0ST\u00a0122"
        }
    },
    {
        "course_reference": {
            "course_number": 799,
            "subjects": [
                "SCANDST"
            ]
        },
        "course_title": "INDEPENDENT STUDY",
        "description": "Faculty-guided in depth study of a topic.",
        "optimized": null,
        "prerequisites": {
            "course_references": [],
            "prerequisites_text": "Consent of instructor"
        }
    },
    {
        "course_reference": {
            "course_number": 201,
            "subjects": [
                "SCANDST"
            ]
        },
        "course_title": "SECOND YEAR NORWEGIAN",
        "description": "Reading of selections from Norwegian writers, grammar review and conversation.",
        "optimized": null,
        "prerequisites": {
            "course_references": [
                {
                    "course_number": 102,
                    "subjects": [
                        "SCANDST"
                    ]
                }
            ],
            "prerequisites_text": "SCAND\u00a0ST\u00a0102"
        }
    },
    {
        "course_reference": {
            "course_number": 699,
            "subjects": [
                "SCANDST"
            ]
        },
        "course_title": "DIRECTED STUDY",
        "description": "Advanced directed study projects as arranged with a faculty member.",
        "optimized": null,
        "prerequisites": {
            "course_references": [],
            "prerequisites_text": "Consent of instructor"
        }
    },
    {
        "course_reference": {
            "course_number": 444,
            "subjects": [
                "SCANDST",
                "MEDIEVAL"
            ]
        },
        "course_title": "KALEVALA AND FINNISH FOLK-LORE",
        "description": "Kalevala - the national epic of Finaland - and the oral literature of Finland.",
        "optimized": null,
        "prerequisites": {
            "course_references": [],
            "prerequisites_text": "Junior standing"
        }
    },
    {
        "course_reference": {
            "course_number": 408,
            "subjects": [
                "SCANDST",
                "MEDIEVAL"
            ]
        },
        "course_title": "INTERMEDIATE OLD NORSE",
        "description": "Designed with a linguistic purpose: to obtain a reading knowledge of Old Norse-Icelandic through the study of Old Icelandic grammar and selections of Old Norse-Icelandic texts.",
        "optimized": null,
        "prerequisites": {
            "course_references": [
                {
                    "course_number": 407,
                    "subjects": [
                        "SCANDST",
                        "MEDIEVAL"
                    ]
                }
            ],
            "prerequisites_text": "SCAND\u00a0ST/\u200bMEDIEVAL\u00a0\u00a0407"
        }
    },
    {
        "course_reference": {
            "course_number": 251,
            "subjects": [
                "SCANDST"
            ]
        },
        "course_title": "READINGS IN NORWEGIAN LITERATURE",
        "description": "Prose, poetry, and drama read in Norwegian. Taught extensively in Norwegian.",
        "optimized": null,
        "prerequisites": {
            "course_references": [
                {
                    "course_number": 202,
                    "subjects": [
                        "SCANDST"
                    ]
                }
            ],
            "prerequisites_text": "SCAND\u00a0ST\u00a0202"
        }
    },
    {
        "course_reference": {
            "course_number": 401,
            "subjects": [
                "SCANDST"
            ]
        },
        "course_title": "CONTEMPORARY SCANDINAVIAN LANGUAGES",
        "description": "Intensive work in spoken and written Danish, Norwegian, and Swedish, based on contemporary readings.",
        "optimized": {
            "course_number": 271,
            "subjects": [
                "SCANDST"
            ]
        },
        "prerequisites": {
            "course_references": [
                {
                    "course_number": 251,
                    "subjects": [
                        "SCANDST"
                    ]
                },
                {
                    "course_number": 261,
                    "subjects": [
                        "SCANDST"
                    ]
                },
                {
                    "course_number": 271,
                    "subjects": [
                        "SCANDST"
                    ]
                }
            ],
            "prerequisites_text": "SCAND\u00a0ST\u00a0251,261,271, or graduate/professional standing"
        }
    },
    {
        "course_reference": {
            "course_number": 422,
            "subjects": [
                "SCANDST"
            ]
        },
        "course_title": "THE DRAMA OF HENRIK IBSEN",
        "description": "Intensive study of dramatic production and the part played by Ibsen as the founder of modern drama.",
        "optimized": {
            "course_number": 222,
            "subjects": [
                "SCANDST"
            ]
        },
        "prerequisites": {
            "course_references": [
                {
                    "course_number": 202,
                    "subjects": [
                        "SCANDST"
                    ]
                },
                {
                    "course_number": 212,
                    "subjects": [
                        "SCANDST"
                    ]
                },
                {
                    "course_number": 222,
                    "subjects": [
                        "SCANDST"
                    ]
                }
            ],
            "prerequisites_text": "SCAND\u00a0ST\u00a0202,212,222or graduate/professional standing"
        }
    },
    {
        "course_reference": {
            "course_number": 411,
            "subjects": [
                "SCANDST"
            ]
        },
        "course_title": "AREAS IN SCANDINAVIAN LITERATURE",
        "description": "Concentrated study of topics within Scandinavian literature.",
        "optimized": {
            "course_number": 261,
            "subjects": [
                "SCANDST"
            ]
        },
        "prerequisites": {
            "course_references": [
                {
                    "course_number": 251,
                    "subjects": [
                        "SCANDST"
                    ]
                },
                {
                    "course_number": 261,
                    "subjects": [
                        "SCANDST"
                    ]
                },
                {
                    "course_number": 271,
                    "subjects": [
                        "SCANDST"
                    ]
                }
            ],
            "prerequisites_text": "SCAND\u00a0ST\u00a0251,261,271, or graduate/professional standing"
        }
    },
    {
        "course_reference": {
            "course_number": 355,
            "subjects": [
                "SCANDST"
            ]
        },
        "course_title": "AUTOBIOGRAPHY",
        "description": "Investigate the genre of autobiography in historical, cultural, and literary contexts, with a highlight of Nordic authors. Analyze autobiographical writing in the context of race, ethnicity, gender, and sexuality, while problematizing concepts such as \"fiction,\" \"truth\" and \"self.\"",
        "optimized": null,
        "prerequisites": {
            "course_references": [],
            "prerequisites_text": "Sophomore standing"
        }
    },
    {
        "course_reference": {
            "course_number": 438,
            "subjects": [
                "GEN&WS",
                "SCANDST",
                "LITTRANS"
            ]
        },
        "course_title": "SEXUAL POLITICS IN SCANDINAVIA",
        "description": "Read and discuss works by Scandinavian writers of the nineteenth and twentieth century reflecting sexual politics and the roles of women in literature. Course taught in English.",
        "optimized": null,
        "prerequisites": {
            "course_references": [],
            "prerequisites_text": "Sophomore standing"
        }
    },
    {
        "course_reference": {
            "course_number": 698,
            "subjects": [
                "SCANDST"
            ]
        },
        "course_title": "DIRECTED STUDY",
        "description": "Advanced directed study projects as arranged with a faculty member.",
        "optimized": null,
        "prerequisites": {
            "course_references": [],
            "prerequisites_text": "Consent of instructor"
        }
    },
    {
        "course_reference": {
            "course_number": 436,
            "subjects": [
                "SCANDST"
            ]
        },
        "course_title": "TOPICS IN SCANDINAVIAN LITERATURE",
        "description": "An examination of selected topics in Scandinavian literature.",
        "optimized": null,
        "prerequisites": {
            "course_references": [],
            "prerequisites_text": "Sophomore standing"
        }
    },
    {
        "course_reference": {
            "course_number": 202,
            "subjects": [
                "SCANDST"
            ]
        },
        "course_title": "SECOND YEAR NORWEGIAN",
        "description": "Rapid reading of suitable Norwegian texts by modern writers.",
        "optimized": null,
        "prerequisites": {
            "course_references": [
                {
                    "course_number": 201,
                    "subjects": [
                        "SCANDST"
                    ]
                }
            ],
            "prerequisites_text": "SCAND\u00a0ST\u00a0201"
        }
    },
    {
        "course_reference": {
            "course_number": 435,
            "subjects": [
                "SCANDST",
                "LITTRANS"
            ]
        },
        "course_title": "THE SAGAS OF ICELANDERS IN ENGLISH TRANSLATION",
        "description": "The prose narratives of medieval Iceland. Gain an understanding of saga literature as a genre and of the cultural history of Iceland in the Viking Era and the Middle Ages, based on the interplay between pagan codes of honor and Christian ethics. In addition, gain an understanding of the methodological problems involved in studying sagas as historical documents.",
        "optimized": null,
        "prerequisites": {
            "course_references": [],
            "prerequisites_text": "Sophomore standing"
        }
    },
    {
        "course_reference": {
            "course_number": 990,
            "subjects": [
                "SCANDST"
            ]
        },
        "course_title": "RESEARCH AND THESIS",
        "description": "Advanced level mentored reading and research for students with dissertator status.",
        "optimized": null,
        "prerequisites": {
            "course_references": [],
            "prerequisites_text": "Consent of instructor"
        }
    },
    {
        "course_reference": {
            "course_number": 112,
            "subjects": [
                "SCANDST"
            ]
        },
        "course_title": "SECOND SEMESTER SWEDISH",
        "description": "For beginning learners of Swedish; emphasis on proficiency through speaking, listening, reading, and writing, and on communication in cultural context.",
        "optimized": null,
        "prerequisites": {
            "course_references": [
                {
                    "course_number": 111,
                    "subjects": [
                        "SCANDST"
                    ]
                }
            ],
            "prerequisites_text": "SCAND\u00a0ST\u00a0111"
        }
    },
    {
        "course_reference": {
            "course_number": 682,
            "subjects": [
                "SCANDST"
            ]
        },
        "course_title": "SENIOR HONORS THESIS",
        "description": "Mentored individual research and study for students completing a thesis in an Honors program.",
        "optimized": null,
        "prerequisites": {
            "course_references": [],
            "prerequisites_text": "Consent of instructor"
        }
    },
    {
        "course_reference": {
            "course_number": 510,
            "subjects": [
                "SCANDST"
            ]
        },
        "course_title": "TOPICS IN SCANDINAVIAN LINGUISTICS",
        "description": "Hands-on introduction to a topic in Scandinavian language study.",
        "optimized": null,
        "prerequisites": {
            "course_references": [],
            "prerequisites_text": "Graduate/professional standing"
        }
    },
    {
        "course_reference": {
            "course_number": 404,
            "subjects": [
                "SCANDST"
            ]
        },
        "course_title": "LANGUAGES OF NORTHERN EUROPE",
        "description": "Introduction to languages of Northern Europe not covered by other department courses (e.g., Sami, Estonian). Practice in language, accompanied by introduction to grammar, culture, and literature. Other language-related topics offered occasionally; check timetable for details.",
        "optimized": null,
        "prerequisites": {
            "course_references": [],
            "prerequisites_text": "Sophomore standing"
        }
    },
    {
        "course_reference": {
            "course_number": 373,
            "subjects": [
                "SCANDST"
            ]
        },
        "course_title": "MASTERPIECES OF SCANDINAVIAN LITERATURE: FROM THE MIDDLE AGES TO 1900",
        "description": "During the late Middle Ages, Scandinavian literature reached its first high point: The Old Norse sagas and poems. Study Scandinavian literature from the sagas to the prose and drama of the golden age of the late 19th century.",
        "optimized": {
            "course_number": 202,
            "subjects": [
                "SCANDST"
            ]
        },
        "prerequisites": {
            "course_references": [
                {
                    "course_number": 202,
                    "subjects": [
                        "SCANDST"
                    ]
                },
                {
                    "course_number": 212,
                    "subjects": [
                        "SCANDST"
                    ]
                },
                {
                    "course_number": 222,
                    "subjects": [
                        "SCANDST"
                    ]
                }
            ],
            "prerequisites_text": "SCAND\u00a0ST\u00a0202,212, or222"
        }
    },
    {
        "course_reference": {
            "course_number": 476,
            "subjects": [
                "SCANDST"
            ]
        },
        "course_title": "SCANDINAVIAN LIFE AND CIVILIZATION II",
        "description": "Scandinavian culture in all its aspects ranging from past history up to contemporary trends in politics and ideologies.",
        "optimized": {
            "course_number": 212,
            "subjects": [
                "SCANDST"
            ]
        },
        "prerequisites": {
            "course_references": [
                {
                    "course_number": 202,
                    "subjects": [
                        "SCANDST"
                    ]
                },
                {
                    "course_number": 212,
                    "subjects": [
                        "SCANDST"
                    ]
                },
                {
                    "course_number": 222,
                    "subjects": [
                        "SCANDST"
                    ]
                }
            ],
            "prerequisites_text": "SCAND\u00a0ST\u00a0202,212,222or graduate/professional standing"
        }
    }
]