[
    {
        "AAE": "#5e8512"
    },
    {
        "MICROBIO": "#5aca07"
    },
    {
        "PHYSICS": "#ec1f1f"
    },
    {
        "CIVENGR": "#b9bc0a"
    },
    {
        "STAT": "#34acb5"
    },
    {
        "CHEM": "#a624fa"
    },
    {
        "GEOSCI": "#0fb0e1"
    },
    {
        "MATH": "#bd33b5"
    },
    {
        "COMPSCI": "#6c92b3"
    },
    {
        "ME": "#2b8ad8"
    },
    {
        "ECON": "#827eaf"
    },
    {
        "EMA": "#7ab2ee"
    },
    {
        "ECE": "#653f65"
    }
]