{
    "course_reference": {
        "course_number": 232,
        "subjects": [
            "ART"
        ]
    },
    "course_title": "LIFE DRAWING I",
    "description": "Anatomical structure and intrinsic forms involved in drawing from different models. Development of technical control in a range of media.",
    "optimized_prerequisites": {
        "course_references": [
            {
                "course_number": 208,
                "subjects": [
                    "ART"
                ]
            },
            {
                "course_number": 212,
                "subjects": [
                    "ART"
                ]
            },
            {
                "course_number": 108,
                "subjects": [
                    "ART"
                ]
            },
            {
                "course_number": 100,
                "subjects": [
                    "ART"
                ]
            }
        ],
        "prerequisites_text": "ART\u00a0212and (ART\u00a0100,108, or208)"
    },
    "prerequisites": {
        "course_references": [
            {
                "course_number": 208,
                "subjects": [
                    "ART"
                ]
            },
            {
                "course_number": 212,
                "subjects": [
                    "ART"
                ]
            },
            {
                "course_number": 108,
                "subjects": [
                    "ART"
                ]
            },
            {
                "course_number": 100,
                "subjects": [
                    "ART"
                ]
            }
        ],
        "prerequisites_text": "ART\u00a0212and (ART\u00a0100,108, or208)"
    }
}