{
    "course_reference": {
        "course_number": 125,
        "subjects": [
            "COUNPSY"
        ]
    },
    "course_title": "THE WISCONSIN EXPERIENCE SEMINAR",
    "description": "Examine transition to UW-Madison through exploration of the research university and the Wisconsin Experience. A variety of texts, including a novel and textbook, will provide a context for discussion, writing, and experiential assignments.",
    "optimized": null,
    "prerequisites": {
        "course_references": [],
        "prerequisites_text": "First year students or first year transfer students only"
    }
}