{
    "course_reference": {
        "course_number": 790,
        "subjects": [
            "CS&D"
        ]
    },
    "course_title": "PRACTICUM IN COMMUNICATIVE DISORDERS",
    "description": "Supervised experience with persons manifesting communicative problems. Evaluation, rehabilitation, and conservation of hearing, language, and speech disorders in various clinical settings.",
    "optimized_prerequisites": {
        "course_references": [],
        "prerequisites_text": "Declared in Communication Sciences & Disorders MS"
    },
    "prerequisites": {
        "course_references": [],
        "prerequisites_text": "Declared in Communication Sciences & Disorders MS"
    }
}