{
    "course_reference": {
        "course_number": 711,
        "subjects": [
            "ECON"
        ]
    },
    "course_title": "ECONOMIC THEORY-MICROECONOMICS SEQUENCE",
    "description": "First course in a two-semester sequence: theories of firms, consumers, and markets; or partial and general equilibria in market and centralized economies; topics in welfare economics. It is expected that students will have completed three semesters calculus (such asMATH\u00a0234) and linear algebra (such asMATH\u00a0340).",
    "optimized": null,
    "prerequisites": {
        "course_references": [],
        "prerequisites_text": "Graduate/professional standing"
    }
}