{
    "course_reference": {
        "course_number": 887,
        "subjects": [
            "ELPA"
        ]
    },
    "course_title": "DIVERSITY AND INEQUALITY IN HIGHER EDUCATION",
    "description": "Survey of equity issues related to higher education access, admissions, transitions, persistence, and success. Focuses on the role of inequities across categories such as race, class, sex, gender, sexual orientation, language, nationality, or religion in higher education alongside considerations as to how researchers and practitioners can better communicate with one another about diversity issues.",
    "prerequisites": {
        "course_references": [],
        "prerequisites_text": "Graduate/professional standing"
    }
}