{
    "course_reference": {
        "course_number": 399,
        "subjects": [
            "GENBUS"
        ]
    },
    "course_title": "READING AND RESEARCH-BUSINESS RESEARCH",
    "description": "Individual work suited to the needs of undergraduate students may be arranged with a faculty member.",
    "optimized_prerequisites": {
        "course_references": [],
        "prerequisites_text": "Consent of instructor"
    },
    "prerequisites": {
        "course_references": [],
        "prerequisites_text": "Consent of instructor"
    }
}