{
    "course_reference": {
        "course_number": 777,
        "subjects": [
            "GEOG"
        ]
    },
    "course_title": "CAPSTONE IN GIS DEVELOPMENT",
    "description": "Covers practical and challenging cases in GIS which require programming and other GIS development skills (such as geospatial algorithm development and implementation). Cases cover the wide spectrum of GIS development projects in the GIS professions ranging from GIS data management, advanced spatial analysis, spatial database development and web/mobile programming, to cartography/geovisualization. Focuses on integration of skills from other courses into a GIS development project.",
    "prerequisites": {
        "course_references": [
            {
                "course_number": 575,
                "subjects": [
                    "GEOG"
                ]
            },
            {
                "course_number": 378,
                "subjects": [
                    "GEOG"
                ]
            },
            {
                "course_number": 572,
                "subjects": [
                    "GEOG"
                ]
            },
            {
                "course_number": 579,
                "subjects": [
                    "GEOG"
                ]
            },
            {
                "course_number": 574,
                "subjects": [
                    "GEOG"
                ]
            },
            {
                "course_number": 576,
                "subjects": [
                    "GEOG"
                ]
            }
        ],
        "prerequisites_text": "GEOG\u00a0378,572,574,575,576,579and graduate/professional standing"
    }
}