{
    "course_reference": {
        "course_number": 332,
        "subjects": [
            "GNS"
        ]
    },
    "course_title": "SECOND SEMESTER KAZAKH",
    "description": "Building on skills learned in first semester Kazakh, learn to communicate in more extended situations. Information on holidays, traditions and colloquial phrases will be introduced. Pays special attention to reading and writing and to vocabulary expansion.",
    "optimized": null,
    "prerequisites": {
        "course_references": [
            {
                "course_number": 331,
                "subjects": [
                    "GNS"
                ]
            }
        ],
        "prerequisites_text": "GNS\u00a0331(or LCA LANG 331 prior to fall 2018)"
    }
}