{
    "course_reference": {
        "course_number": 323,
        "subjects": [
            "HISTORY",
            "HISTSCI"
        ]
    },
    "course_title": "THE SCIENTIFIC REVOLUTION: FROM COPERNICUS TO NEWTON",
    "description": "An introduction to the formative period of modern science, including major ideas and events in the physical and life sciences from Copernicus to Newton.",
    "optimized_prerequisites": {
        "course_references": [
            {
                "course_number": 623,
                "subjects": [
                    "HISTSCI"
                ]
            }
        ],
        "prerequisites_text": "Junior standing or (graduate/professional standing and concurrent enrollment inHIST\u00a0SCI\u00a0623)"
    },
    "prerequisites": {
        "course_references": [
            {
                "course_number": 623,
                "subjects": [
                    "HISTSCI"
                ]
            }
        ],
        "prerequisites_text": "Junior standing or (graduate/professional standing and concurrent enrollment inHIST\u00a0SCI\u00a0623)"
    }
}