{
    "course_reference": {
        "course_number": 524,
        "subjects": [
            "LATIN"
        ]
    },
    "course_title": "ROMAN NOVEL",
    "description": "One or a combination of : Petronius, Cena Trimalchionis, Satyricon; Apuleius, Cupid and Psyche, Metamorphoses; other Roman novels.",
    "optimized_prerequisites": {
        "course_references": [],
        "prerequisites_text": "None"
    },
    "prerequisites": {
        "course_references": [],
        "prerequisites_text": "None"
    }
}