{
    "course_reference": {
        "course_number": 690,
        "subjects": [
            "LINGUIS"
        ]
    },
    "course_title": "CAPSTONE IN LINGUISTICS",
    "description": "In-depth exploration of a particular topic in linguistics. Training in data collection methodologies. Experience gathering, organizing, and analyzing linguistic data as part of a supervised research project.",
    "prerequisites": {
        "course_references": [
            {
                "course_number": 322,
                "subjects": [
                    "LINGUIS"
                ]
            },
            {
                "course_number": 310,
                "subjects": [
                    "LINGUIS"
                ]
            },
            {
                "course_number": 330,
                "subjects": [
                    "LINGUIS"
                ]
            }
        ],
        "prerequisites_text": "LINGUIS\u00a0310,322, and330"
    }
}