{
    "course_reference": {
        "course_number": 350,
        "subjects": [
            "LITTRANS"
        ]
    },
    "course_title": "SCANDINAVIAN DECADENCE IN ITS EUROPEAN CONTEXT",
    "description": "Examines the European context of literary decadence (Baudelaire, Huysmans, Wilde) and how it inspired some of Scandinavia's most important writers (Strindberg, Hamsun, Jacobsen).",
    "optimized": null,
    "prerequisites": {
        "course_references": [],
        "prerequisites_text": "Junior standing"
    }
}