{
    "course_reference": {
        "course_number": 332,
        "subjects": [
            "LSC"
        ]
    },
    "course_title": "DIGITAL AND PRINT MEDIA DESIGN",
    "description": "Principles and techniques of effective visual communication with industry-standard digital design software for use in digital and print publications.",
    "optimized_prerequisites": {
        "course_references": [],
        "prerequisites_text": "None"
    },
    "prerequisites": {
        "course_references": [],
        "prerequisites_text": "None"
    }
}