{
    "course_reference": {
        "course_number": 552,
        "subjects": [
            "MATH"
        ]
    },
    "course_title": "ELEMENTARY GEOMETRIC AND ALGEBRAIC TOPOLOGY",
    "description": "Introduction to algebraic topology. Emphasis on geometric aspects, including two-dimensional manifolds, the fundamental group, covering spaces, basic simplicial homology theory, the Euler-Poincare formula, and homotopy classes of mappings.",
    "optimized_prerequisites": {
        "course_references": [
            {
                "course_number": 551,
                "subjects": [
                    "MATH"
                ]
            },
            {
                "course_number": 541,
                "subjects": [
                    "MATH"
                ]
            }
        ],
        "prerequisites_text": "(MATH\u00a0551and541) or graduate/professional standing or member of the Pre-Masters Mathematics (Visiting International) Program"
    },
    "prerequisites": {
        "course_references": [
            {
                "course_number": 551,
                "subjects": [
                    "MATH"
                ]
            },
            {
                "course_number": 541,
                "subjects": [
                    "MATH"
                ]
            }
        ],
        "prerequisites_text": "(MATH\u00a0551and541) or graduate/professional standing or member of the Pre-Masters Mathematics (Visiting International) Program"
    }
}