{
    "course_reference": {
        "course_number": 471,
        "subjects": [
            "ME"
        ]
    },
    "course_title": "GAS TURBINE AND JET PROPULSION",
    "description": "Principles of thermodynamics and fluid dynamics utilized in the analysis and design of gas-turbine cycles, components and systems for stationary, automotive and aircraft applications.",
    "optimized": null,
    "prerequisites": {
        "course_references": [
            {
                "course_number": 364,
                "subjects": [
                    "ME"
                ]
            }
        ],
        "prerequisites_text": "M\u00a0E\u00a0364, graduate/professional standing, or member of Engineering Guest Students"
    }
}