{
    "course_reference": {
        "course_number": 725,
        "subjects": [
            "NURSING"
        ]
    },
    "course_title": "POPULATION HEALTH THEORY AND METHODS SEMINAR III: EMERGING ISSUES AND SPECIALIZED ROLES",
    "description": "Explore specialized roles, emerging issues, and current priorities in advanced population health nursing. Analyze novel and emergent population health challenges within context, and consider the unique knowledge, skills, and philosophies that prepared nurses can bring to solution-seeking and interdisciplinary efforts to promote or safeguard population health.",
    "optimized": {
        "course_number": 724,
        "subjects": [
            "NURSING"
        ]
    },
    "prerequisites": {
        "course_references": [
            {
                "course_number": 724,
                "subjects": [
                    "NURSING"
                ]
            }
        ],
        "prerequisites_text": "NURSING\u00a0724"
    }
}