{
    "course_reference": {
        "course_number": 304,
        "subjects": [
            "PHILOS"
        ]
    },
    "course_title": "TOPICS IN PHILOSOPHY: HUMANITIES",
    "description": "Examination of selected topics in philosophy.",
    "enrollment_data": {
        "credit_count": [
            3,
            4
        ],
        "ethnics_studies": false,
        "general_education": false,
        "instructors": {},
        "last_taught_term_code": 1222,
        "school": "{\n    \"name\": \"Letters and Science\",\n    \"abbreviation\": \"L\",\n    \"url\": \"http://www.ls.wisc.edu/\"\n}",
        "typically_offered": "Occasionally"
    },
    "madgrades_data": {
        "by_term": {
            "Fall 2013": {
                "a": 7,
                "ab": 3,
                "b": 4,
                "bc": 2,
                "c": 2,
                "credit": 0,
                "d": 0,
                "f": 0,
                "incomplete": 0,
                "no_credit": 0,
                "no_work": 0,
                "not_reported": 0,
                "other": 0,
                "passed": 0,
                "satisfactory": 3,
                "total": 21,
                "unsatisfactory": 0
            },
            "Fall 2015": {
                "a": 34,
                "ab": 0,
                "b": 0,
                "bc": 0,
                "c": 0,
                "credit": 0,
                "d": 0,
                "f": 0,
                "incomplete": 0,
                "no_credit": 0,
                "no_work": 0,
                "not_reported": 0,
                "other": 0,
                "passed": 0,
                "satisfactory": 0,
                "total": 34,
                "unsatisfactory": 0
            },
            "Fall 2017": {
                "a": 31,
                "ab": 15,
                "b": 10,
                "bc": 3,
                "c": 3,
                "credit": 0,
                "d": 1,
                "f": 1,
                "incomplete": 1,
                "no_credit": 0,
                "no_work": 0,
                "not_reported": 0,
                "other": 0,
                "passed": 0,
                "satisfactory": 2,
                "total": 67,
                "unsatisfactory": 0
            },
            "Fall 2018": {
                "a": 54,
                "ab": 16,
                "b": 5,
                "bc": 2,
                "c": 2,
                "credit": 0,
                "d": 1,
                "f": 0,
                "incomplete": 0,
                "no_credit": 0,
                "no_work": 0,
                "not_reported": 0,
                "other": 0,
                "passed": 0,
                "satisfactory": 0,
                "total": 80,
                "unsatisfactory": 0
            },
            "Fall 2019": {
                "a": 4,
                "ab": 15,
                "b": 6,
                "bc": 1,
                "c": 0,
                "credit": 0,
                "d": 0,
                "f": 0,
                "incomplete": 0,
                "no_credit": 0,
                "no_work": 0,
                "not_reported": 0,
                "other": 0,
                "passed": 0,
                "satisfactory": 0,
                "total": 26,
                "unsatisfactory": 0
            },
            "Fall 2021": {
                "a": 25,
                "ab": 7,
                "b": 3,
                "bc": 0,
                "c": 0,
                "credit": 0,
                "d": 0,
                "f": 0,
                "incomplete": 3,
                "no_credit": 0,
                "no_work": 2,
                "not_reported": 0,
                "other": 0,
                "passed": 0,
                "satisfactory": 0,
                "total": 40,
                "unsatisfactory": 0
            },
            "Fall 2023": {
                "a": 13,
                "ab": 1,
                "b": 0,
                "bc": 0,
                "c": 0,
                "credit": 0,
                "d": 0,
                "f": 0,
                "incomplete": 0,
                "no_credit": 0,
                "no_work": 0,
                "not_reported": 0,
                "other": 0,
                "passed": 0,
                "satisfactory": 0,
                "total": 14,
                "unsatisfactory": 0
            },
            "Spring 2011": {
                "a": 17,
                "ab": 2,
                "b": 1,
                "bc": 0,
                "c": 0,
                "credit": 0,
                "d": 0,
                "f": 0,
                "incomplete": 0,
                "no_credit": 0,
                "no_work": 0,
                "not_reported": 0,
                "other": 0,
                "passed": 0,
                "satisfactory": 1,
                "total": 21,
                "unsatisfactory": 0
            },
            "Spring 2017": {
                "a": 31,
                "ab": 23,
                "b": 6,
                "bc": 0,
                "c": 0,
                "credit": 0,
                "d": 0,
                "f": 0,
                "incomplete": 0,
                "no_credit": 0,
                "no_work": 0,
                "not_reported": 0,
                "other": 0,
                "passed": 0,
                "satisfactory": 4,
                "total": 64,
                "unsatisfactory": 0
            },
            "Spring 2018": {
                "a": 35,
                "ab": 26,
                "b": 6,
                "bc": 3,
                "c": 3,
                "credit": 0,
                "d": 0,
                "f": 1,
                "incomplete": 1,
                "no_credit": 0,
                "no_work": 0,
                "not_reported": 0,
                "other": 0,
                "passed": 0,
                "satisfactory": 1,
                "total": 77,
                "unsatisfactory": 1
            },
            "Spring 2019": {
                "a": 29,
                "ab": 11,
                "b": 8,
                "bc": 4,
                "c": 1,
                "credit": 0,
                "d": 3,
                "f": 0,
                "incomplete": 0,
                "no_credit": 0,
                "no_work": 1,
                "not_reported": 0,
                "other": 0,
                "passed": 0,
                "satisfactory": 3,
                "total": 60,
                "unsatisfactory": 0
            },
            "Spring 2023": {
                "a": 3,
                "ab": 1,
                "b": 1,
                "bc": 0,
                "c": 0,
                "credit": 0,
                "d": 0,
                "f": 0,
                "incomplete": 0,
                "no_credit": 0,
                "no_work": 0,
                "not_reported": 0,
                "other": 0,
                "passed": 0,
                "satisfactory": 1,
                "total": 6,
                "unsatisfactory": 0
            }
        },
        "cumulative": {
            "a": 283,
            "ab": 120,
            "b": 50,
            "bc": 15,
            "c": 11,
            "credit": 0,
            "d": 5,
            "f": 2,
            "incomplete": 5,
            "no_credit": 0,
            "no_work": 3,
            "not_reported": 0,
            "other": 0,
            "passed": 0,
            "satisfactory": 15,
            "total": 510,
            "unsatisfactory": 1
        }
    },
    "optimized_prerequisites": {
        "course_references": [],
        "prerequisites_text": "Sophomore standing"
    },
    "prerequisites": {
        "course_references": [],
        "prerequisites_text": "Sophomore standing"
    }
}