{
    "course_reference": {
        "course_number": 803,
        "subjects": [
            "PSYCH"
        ]
    },
    "course_title": "ADVANCED TECHNIQUES IN PSYCHOTHERAPY",
    "description": "An overview of empirically supported psychotherapeutic movements and their associated history, philosophical underpinnings, and techniques. Oriented toward the theoretical perspective, basic tenets, and the practical techniques/skills of each psychotherapy.",
    "optimized_prerequisites": {
        "course_references": [],
        "prerequisites_text": "Consent of instructor"
    },
    "prerequisites": {
        "course_references": [],
        "prerequisites_text": "Consent of instructor"
    }
}