{
    "course_reference": {
        "course_number": 985,
        "subjects": [
            "RP&SE"
        ]
    },
    "course_title": "ADVANCED METHODOLOGIES IN DISABILITY & REHABILITATION RESEARCH",
    "description": "Advanced statistical methods, design, instrumentation, and procedures in research and program evaluation in disability and rehabilitation settings.",
    "optimized_prerequisites": {
        "course_references": [],
        "prerequisites_text": "Declared in Rehabilitation Counselor Education"
    },
    "prerequisites": {
        "course_references": [],
        "prerequisites_text": "Declared in Rehabilitation Counselor Education"
    }
}