{
    "course_reference": {
        "course_number": 441,
        "subjects": [
            "SOCWORK"
        ]
    },
    "course_title": "GENERALIST PRACTICE WITH INDIVIDUALS, FAMILIES AND GROUPS",
    "description": "Develops generalist social work knowledge and skills for working with and on behalf of individuals, families, and groups. Focus on development of basic social work direct practice skills.",
    "optimized_prerequisites": {
        "course_references": [],
        "prerequisites_text": "Declared in Social Work BSW or Social Work MSW"
    },
    "prerequisites": {
        "course_references": [],
        "prerequisites_text": "Declared in Social Work BSW or Social Work MSW"
    }
}