{
    "course_reference": {
        "course_number": 305,
        "subjects": [
            "STAT"
        ]
    },
    "course_title": "R FOR STATISTICS III",
    "description": "Provides an understanding of the commonly used statistical language R. Learn to combine R with high performance computing tools to do scientific computing.",
    "prerequisites": {
        "course_references": [
            {
                "course_number": 304,
                "subjects": [
                    "STAT"
                ]
            }
        ],
        "prerequisites_text": "STAT\u00a0304"
    }
}