{
    "course_reference": {
        "course_number": 270,
        "subjects": [
            "THEATRE"
        ]
    },
    "course_title": "FUNDAMENTALS OF STAGECRAFT",
    "description": "Theory and techniques of stagecraft for theatrical production.\u00a0When taken for 4 credits, a lab component required.",
    "optimized_prerequisites": {
        "course_references": [
            {
                "course_number": 160,
                "subjects": [
                    "THEATRE"
                ]
            }
        ],
        "prerequisites_text": "THEATRE\u00a0160"
    },
    "prerequisites": {
        "course_references": [
            {
                "course_number": 160,
                "subjects": [
                    "THEATRE"
                ]
            }
        ],
        "prerequisites_text": "THEATRE\u00a0160"
    }
}