{
    "course_reference": {
        "course_number": 770,
        "subjects": [
            "THEATRE"
        ]
    },
    "course_title": "ADVANCED THEATRE TECHNOLOGY",
    "description": "Detailed study of research and practice in the physical theatre and its scenic devices.",
    "optimized_prerequisites": {
        "course_references": [],
        "prerequisites_text": "Graduate/professional standing"
    },
    "prerequisites": {
        "course_references": [],
        "prerequisites_text": "Graduate/professional standing"
    }
}